numpyDealer/Card.py
numpyDealer/numpyDeck.py
numpyDealer-1.0.2.dist-info/LICENSE.txt
numpyDealer-1.0.2.dist-info/METADATA
numpyDealer-1.0.2.dist-info/WHEEL
numpyDealer-1.0.2.dist-info/entry_points.txt
numpyDealer-1.0.2.dist-info/top_level.txt
numpyDealer-1.0.2.dist-info/RECORD
