Metadata-Version: 2.1
Name: numpyDealer
Version: 1.0.2
Summary: Playing cards in numpy decks.
Home-page: UNKNOWN
Author: Ethan Griffin
Author-email: ethbgriffin@gmail.com
License: MIT
Platform: UNKNOWN
Classifier: License :: OSI Approved :: MIT License
Classifier: Programming Language :: Python :: 3
Classifier: Programming Language :: Python :: 3.8
License-File: LICENSE.txt
Requires-Dist: numpy
